botwinick_math/__init__.py
botwinick_math/geo/__init__.py
botwinick_math/geo/cartesian.py
botwinick_math/geo/circles.py
botwinick_math/geo/grid.py
botwinick_math/geo/transforms_2d.py
botwinick_math/geo/wind.py
botwinick_math/maths/__init__.py
botwinick_math/maths/aggregate.py
botwinick_math/maths/counting.py
botwinick_math/maths/inflit.py
botwinick_math/maths/merge.py
botwinick_math/maths/precision.py
botwinick_math/maths/series.py
botwinick_math/maths/sorted.py
botwinick_math-0.0.5.dist-info/LICENSE
botwinick_math-0.0.5.dist-info/METADATA
botwinick_math-0.0.5.dist-info/WHEEL
botwinick_math-0.0.5.dist-info/top_level.txt
botwinick_math-0.0.5.dist-info/RECORD
