Metadata-Version: 2.1
Name: botwinick-math
Version: 0.0.5
Summary: Assorted Math code
Home-page: https://github.com/dbotwinick/python-botwinick-math
Author: Drew Botwinick
Author-email: foss@drewbotwinick.com
License: UNKNOWN
Platform: UNKNOWN
Classifier: Development Status :: 4 - Beta
Classifier: Intended Audience :: Developers
Classifier: Programming Language :: Python :: 2
Classifier: Programming Language :: Python :: 3
Classifier: License :: OSI Approved :: BSD License
Classifier: Operating System :: OS Independent
Requires-Python: >=2.7, >=3.6
License-File: LICENSE
Requires-Dist: numpy
Requires-Dist: scipy
